flowcast/__init__.py
flowcast/gadm.py
flowcast/pipeline.py
flowcast/regrid.py
flowcast/spacetime.py
flowcast/utilities.py
flowcast-0.5.2.dist-info/LICENSE
flowcast-0.5.2.dist-info/METADATA
flowcast-0.5.2.dist-info/WHEEL
flowcast-0.5.2.dist-info/RECORD
