Metadata-Version: 2.1
Name: flowcast
Version: 0.5.2
Summary: A framework for dynamically stringing together operations over gridded netcdf data, to create derived insights
License: GPL-3.0-or-later
Author: David Samson
Author-email: david@jataware.com
Requires-Python: >=3.8,<3.12
Classifier: License :: OSI Approved :: GNU General Public License v3 or later (GPLv3+)
Classifier: Programming Language :: Python :: 3
Classifier: Programming Language :: Python :: 3.8
Classifier: Programming Language :: Python :: 3.9
Classifier: Programming Language :: Python :: 3.10
Classifier: Programming Language :: Python :: 3.11
Requires-Dist: cftime (>=1.6.2,<2.0.0)
Requires-Dist: geofeather (>=0.3.0,<0.4.0)
Requires-Dist: geopandas (>=0.8.1)
Requires-Dist: matplotlib (>=3.5.2)
Requires-Dist: nc-time-axis (>=1.4.1,<2.0.0)
Requires-Dist: netCDF4 (>=1.5.3)
Requires-Dist: numpy (>=1.22)
Requires-Dist: rasterio (>=1.2.10)
Requires-Dist: requests (>=2.28.1)
Requires-Dist: rich (>=13.5.3,<14.0.0)
Requires-Dist: scikit-learn (>=1.0.2)
Requires-Dist: scipy (>=1.9)
Requires-Dist: tqdm (>=4.64.0)
Requires-Dist: typing-extensions (>=4.8.0,<5.0.0)
Requires-Dist: xarray (>=0.19.0)
